rsi/__init__.py
rsi/citizen.py
rsi/conf.py
rsi/exceptions.py
rsi/hangar.py
rsi/launcher.py
rsi/org.py
rsi/pledge_store.py
rsi/roadmap.py
rsi/rsi.py
rsi/session.py
rsi/shipmatrix.py
rsi/status.py
rsi/utils.py
pyrsi-0.1.19.dist-info/AUTHORS.rst
pyrsi-0.1.19.dist-info/LICENSE
pyrsi-0.1.19.dist-info/METADATA
pyrsi-0.1.19.dist-info/WHEEL
pyrsi-0.1.19.dist-info/top_level.txt
pyrsi-0.1.19.dist-info/zip-safe
pyrsi-0.1.19.dist-info/RECORD
