Metadata-Version: 2.1
Name: pyrsi
Version: 0.1.19
Summary: Python API for interacting with the Roberts Space Industries site for Star Citizen.
Home-page: https://gitlab.com/scmodding/frameworks/pyrsi
Author: Ventorvar
Author-email: ventorvar@gmail.com
License: MIT license
Keywords: pyrsi
Platform: UNKNOWN
Classifier: Development Status :: 2 - Pre-Alpha
Classifier: Intended Audience :: Developers
Classifier: License :: OSI Approved :: MIT License
Classifier: Natural Language :: English
Classifier: Programming Language :: Python :: 3
Classifier: Programming Language :: Python :: 3.8
Requires-Dist: cachetools
Requires-Dist: requests
Requires-Dist: fuzzywuzzy
Requires-Dist: python-Levenshtein
Requires-Dist: beautifulsoup4
Requires-Dist: configparser
